nope_net/__init__.py
nope_net/client.py
nope_net/errors.py
nope_net/py.typed
nope_net/types.py
nope_net/webhook.py
nope_net-1.3.1.dist-info/METADATA
nope_net-1.3.1.dist-info/WHEEL
nope_net-1.3.1.dist-info/RECORD
