Metadata-Version: 2.4
Name: nope-net
Version: 1.3.1
Summary: Python SDK for the NOPE safety API - risk classification for conversations
Project-URL: Homepage, https://nope.net
Project-URL: Documentation, https://nope.net/docs
Project-URL: Repository, https://github.com/nope-net/python-sdk
Author-email: NOPE <support@nope.net>
License: MIT
Keywords: ai,classification,crisis,mental-health,risk,safety
Classifier: Development Status :: 4 - Beta
Classifier: Intended Audience :: Developers
Classifier: License :: OSI Approved :: MIT License
Classifier: Programming Language :: Python :: 3
Classifier: Programming Language :: Python :: 3.9
Classifier: Programming Language :: Python :: 3.10
Classifier: Programming Language :: Python :: 3.11
Classifier: Programming Language :: Python :: 3.12
Classifier: Topic :: Software Development :: Libraries :: Python Modules
Requires-Python: >=3.9
Requires-Dist: httpx>=0.25.0
Requires-Dist: pydantic>=2.0.0
Provides-Extra: dev
Requires-Dist: mypy>=1.0.0; extra == 'dev'
Requires-Dist: pytest-asyncio>=0.21.0; extra == 'dev'
Requires-Dist: pytest-httpx>=0.21.0; extra == 'dev'
Requires-Dist: pytest>=7.0.0; extra == 'dev'
Requires-Dist: ruff>=0.1.0; extra == 'dev'
